cfn_lambda_handler/__init__.py
cfn_lambda_handler/cfn_lambda_handler.py
cfn_lambda_handler-1.4.0.dist-info/LICENSE
cfn_lambda_handler-1.4.0.dist-info/METADATA
cfn_lambda_handler-1.4.0.dist-info/WHEEL
cfn_lambda_handler-1.4.0.dist-info/top_level.txt
cfn_lambda_handler-1.4.0.dist-info/RECORD
